plbdays/__init__.py
plbdays-1.1.1.dist-info/LICENSE.txt
plbdays-1.1.1.dist-info/METADATA
plbdays-1.1.1.dist-info/WHEEL
plbdays-1.1.1.dist-info/top_level.txt
plbdays-1.1.1.dist-info/RECORD
