Metadata-Version: 2.1
Name: plbdays
Version: 1.1.1
Summary: Business days in Poland
Home-page: https://github.com/ZawadzkiR/plbays/
Author: Robert Zawadzki
Author-email: r.zawadzki96@gmail.com
Project-URL: Bug Tracker, https://github.com/ZawadzkiR/plbays/issues
Keywords: business days
License-File: LICENSE.txt
